Workbook
Name _1234567: #REF!
Name _1234567: #REF!
Name _1234567: #REF!
Name _ftn1: 'Себестоимость проекта'!$B$25
Name _ftnref1: 'Себестоимость проекта'!#REF!
Name CY: [1]Список!$D$2
Name hjjtrasgag: #REF!
Name hjjtrasgag: #REF!
Name TB11B: #REF!
Name TB11B: #REF!
Name TR10B: #REF!
Name TR10B: #REF!
Name TR10EXP: #REF!
Name TR10EXP: #REF!
Name TR10PSZ: #REF!
Name TR10PSZ: #REF!
Name TR10S: #REF!
Name TR10S: #REF!
Name TR10ST: #REF!
Name TR10ST: #REF!
Name TR10Y: #REF!
Name TR10Y: #REF!
Name TR11B: #REF!
Name TR11B: #REF!
Name TR11PSZ: #REF!
Name TR11PSZ: #REF!
Name TR11S: #REF!
Name TR11S: #REF!
Name TR11ST: #REF!
Name TR11ST: #REF!
Name TR11Y: #REF!
Name TR11Y: #REF!
Name TR12B: #REF!
Name TR12B: #REF!
Name TR12EXP: #REF!
Name TR12EXP: #REF!
Name TR12PSY: #REF!
Name TR12PSZ: #REF!
Name TR12PSZ: #REF!
Name TR12S: #REF!
Name TR12S: #REF!
Name TR12ST: #REF!
Name TR12ST: #REF!
Name TR12Y: #REF!
Name TR12Y: #REF!
Name TR15B: #REF!
Name TR15B: #REF!
Name TR15EXP: #REF!
Name TR15EXP: #REF!
Name TR15PSZ: #REF!
Name TR15PSZ: #REF!
Name TR15S: #REF!
Name TR15S: #REF!
Name TR15ST: #REF!
Name TR15ST: #REF!
Name TR15Y: #REF!
Name TR15Y: #REF!
Name TR1EXP: #REF!
Name TR1EXP: #REF!
Name TR20B: #REF!

Sheet Оглавление

Sheet Себестоимость проекта
B3: Наименование статей калькуляции | C3: Предложено организацией-поставщиком (подрядчиком, исполнителем) | H3: Примечание
C4: Всего | D4: в том числе:
D5: затраты за 2026 год | E5: затраты за 2027 год | F5: Затраты за 2028 год | G5: Затраты за 2029 год
B6: Материальные затраты - всего: | C6: =C8+C10+C9 -> 7.935314e+08 | D6: =D8+D10+D9 -> 0 | E6: =E8+E10+E9 -> 7.935314e+08 | F6: =F8+F10+F9 -> 0 | G6: =G8+G10+G9 -> 0
B7: в том числе:
B8: приобретение сырья, материалов и вспомогательных материалов | C8: =D8+E8+F8 -> 2.2192336e+08 | E8: ='Материалы '!E21 -> 2.2192336e+08 | F8: ='[4]ф4 мат'!AD10 -> 0
B9: приобретение комплектующих изделий | C9: =D9+E9+F9 -> 345880000 | D9: 0 | E9: =ПКИ!D9 -> 345880000 | F9: 0
B10: транспортно-заготовительные затраты (приняты на уровне % ТЗР, принятого в АО "АВ" | C10: =D10+E10+F10 -> 2.2572804e+08 | E10: =E8+E9*1.1% -> 2.2572804e+08 | F10: =F8*1.1% -> 0
B11: Затраты на оплату труда - всего: | C11: =C13+C14 -> 8.1328286e+08 | D11: =D13+D14 -> 0 | E11: =E13+E14 -> 66272627 | F11: =F13+F14 -> 5.2855223e+08 | G11: =G13+G14 -> 2.18458e+08
B12: в том числе:
B13: основная заработная плата | C13: =SUM(D13:G13) -> 7.1743166e+08 | E13: =ФОТ_ОПР_расчёт!D11 -> 58461924 | F13: =ФОТ_ОПР_расчёт!D21 -> 4.6625858e+08 | G13: =ФОТ_ОПР_расчёт!D26 -> 1.9271116e+08
B14: дополнительная заработная плата | C14: =SUM(D14:G14) -> 95851194 | E14: =ФОТ_ОПР_расчёт!F11 -> 7810702.4 | F14: =ФОТ_ОПР_расчёт!F21 -> 62293656 | G14: =ФОТ_ОПР_расчёт!F26 -> 25746836
B15: Страховые взносы на обязательное социальное страхование | C15: =SUM(D15:G15) -> 2.6675678e+08 | E15: =ФОТ_ОПР_расчёт!H11 -> 21737422 | F15: =ФОТ_ОПР_расчёт!H21 -> 1.7336513e+08 | G15: =ФОТ_ОПР_расчёт!H26 -> 71654224
B16: Общепроизводственные затраты | C16: =D16+E16+F16 -> 0 | E16: 0 | F16: 0
B17: Общехозяйственные затраты | C17: =D17+E17+F17 -> 0 | E17: 0 | F17: 0
B18: Прочие прямые затраты
B19: Производственная себестоимость (сумма строк 0100, 0200, 0300, 0400, 0500 – 1200) | C19: =SUM(D19:G19) -> 1.5834588e+09 | E19: =E6+E11+E15+E16+E17+E18 -> 8.8154145e+08 | F19: =F6+F11+F15+F16+F17+F18 -> 7.0191736e+08
B20: Коммерческие (внепроизводственные) затраты
B21: Себестоимость продукции (сумма строк 1300, 1400, 1500, 1600) | C21: =C19 -> 1.5834588e+09 | D21: =D19 -> 0 | E21: =E19 -> 8.8154145e+08 | F21: =F19 -> 7.0191736e+08
B22: в том числе:
B23: привнесенные затраты | C23: =D23+E23+F23 -> 0 | F23: ='[4]20 (20д) приб'!N44 -> 0
B24: собственные затраты | C24: =D24+E24+F24 -> 0 | E24: ='[4]20 (20д) приб'!H44 -> 0 | F24: ='[4]20 (20д) приб'!M44 -> 0
B25: Прибыль | D25: Х | E25: Х | F25: Х
B26: Цена продукции (без НДС) (сумма строк 1700, 1800) | C26: =C25+C21 -> 1.5834588e+09 | D26: Х | E26: Х | F26: Х
B27: Трудоемкость (нормо-часы) | C27: =SUM(D27:G27) -> 611468.55 | E27: ='Расчёт трудоемкости'!E16 -> 53834.18 | F27: ='Расчёт трудоемкости'!F16 -> 390644.43 | G27: ='Расчёт трудоемкости'!G16 -> 166989.94

Sheet Материалы 
A2: Расшифровка затрат на на приобретение сырья, материалов и вспомогательных материалов
A4: Наименование материала | B4: Единица измерения | C4: Количество | D4: Цена за единицу, без НДС | E4: Сумма | F4: Поставщик | G4: Ссылка
A5: Лист горячекатаный судостр 10х1600х6000, марка РС B | B5: т | C5: 660 | D5: =(70000/1.22)*1.052 -> 60360.656 | E5: =C5*D5 -> 39838033 | F5: АО "Металлсервис" | G5: https://mc.ru/metalloprokat/stal_listovaya_g_k_sudostroitelnaya
A6: Лист стальной 24х2000х6000 мм D36 ГОСТ Р 52927-2015 | B6: т | C6: 55 | D6: =(45011/1.22)*1.052 -> 38812.764 | E6: =C6*D6 -> 2134702 | F6: Торговая площадка "Пульс цен" | G6: https://ekb.pulscen.ru/products/list_stalnoy_24kh2000kh6000_mm_d36_gost_r_52927_2015_303060267
A7: Лист горячекатаный низколегир 6х1500х6000, марка 09Г2С-15 | B7: т | C7: 253 | D7: =(70990/1.22)*1.052 -> 61214.328 | E7: =C7*D7 -> 15487225 | F7: АО "Металлсервис" | G7: Металлсервис: Лист 09Г2С
A8: Швеллер низколегированный 12 П, длина 12 м, марка 09Г2С-15 | B8: т | C8: 234 | D8: =(112490/1.22)*1.052 -> 96999.574 | E8: =C8*D8 -> 22697900 | F8: АО "Металлсервис" | G8: https://mc.ru/metalloprokat/shveller_nizkolegirovannyy_12_p_razmer_12_marka_09g2s-15_dlina_12000
A9: Алюминиевый лист АМг5М РМРС 6х1500х4000 | B9: кг | C9: 130000 | D9: =700*1.043 -> 730.1 | E9: =C9*D9 -> 94913000 | F9: ООО "Невская Алюминиевая Компания" | G9: СПбАлюм: лист АМг5
A10: Тавр алюминиевый АМг5 20х20х2 ГОСТ 13622-91 | B10: т | C10: 23 | D10: =(296060/1.22)*1.052 -> 255291.08 | E10: =C10*D10 -> 5871694.9 | F10: "Металл-союз" | G10: https://metsklad.ru/tavr-alyuminievyij/tavr-alyuminievyij-amg5-20x20x2-gost-13622-91/?spm=a2ty_o01.29997173.0.0.51c855fb33pSyd
A11: Алюминиевый уголок АМг5 50х30х3,0х6000 уголок 410944 | B11: т | C11: 4.8 | D11: =((1600*1000)/1.22)*1.052 -> 1379672.1 | E11: =C11*D11 -> 6622426.2 | F11: ПКФ "Металл СВ" | G11: https://www.sv-metal.ru/catalog/alluminiy/alyuminievyy-ugolok/amg5-50h30h3-0-l-6000-410944/?spm=a2ty_o01.29997173.0.0.51c855fb33pSyd
A12: Алюминиевый уголок АМГ5 40х25х4 | B12: т | C12: 3.2 | D12: =(408500/1.22)*1.052 -> 352247.54 | E12: =C12*D12 -> 1127192.1 | F12: Компания Мост | G12: https://moststal.ru/magazin/alyuminievyij-ugolok-amg5-40x25x4?spm=a2ty_o01.29997173.0.0.51c855fb33pSyd
A13: Труба бесшовная (DN40–DN125), Ст20/09Г2С, ГОСТ 8732 | B13: т | C13: 75.4 | D13: =(158870/1.22)*1.04 -> 135430.16 | E13: =C13*D13 -> 10211434 | F13: ООО " МК "Буран" | G13: https://spb.buranmetall.ru/truba-besshovnaya-09g2s/40x9?ysclid=muel5e80ub913359280
A14: Труба бесшовная (DN20–DN80), 12Х18Н10Т (316L) | B14: кг | C14: 38.1 | D14: =(811/1.22)*1.04 -> 691.34426 | E14: =C14*D14 -> 26340.216 | F14: ООО ТК ИноксМаркет | G14: InoxMarket: 12Х18Н10Т
A15: Труба ПНД/ПП (DN50–DN225), судовая негорючая | B15: м | C15: 8.9 | D15: =(205/1.22)*1.04 -> 174.7541 | E15: =C15*D15 -> 1555.3115 | F15: Компания Энерго Пайп | G15: https://energo-pipe.ru/
A16: Судовая арматура, фланцы, клапаны (PTFE для метанола) | B16: шт. | C16: 50 | D16: =(12684/1.22)*1.042 -> 10833.384 | E16: =C16*D16 -> 541669.18 | F16: ООО "ТД Ватервальве" | G16: https://shop-watervalve.ru/59137/
A17: Кабель силовой, контрольный, огнестойкий, слаботочный | B17: м | C17: 55 | D17: =(49.8/1.22)*1.042 -> 42.534098 | E17: =C17*D17 -> 2339.3754 | F17: ООО "СнапКабель" | G17: https://snabcable.ru/about_us/
A18: Кабельные трассы (лотки ДКС), сальники, проходки | B18: м | C18: 25 | D18: =(470.64/1.22)*1.042 -> 401.97285 | E18: =C18*D18 -> 10049.321 | F18: АО "ДКС" | G18: https://dkc-msk.ru/products/lotok-perforirovannyy-100kh50-l3000-35262/
A19: Грунт эпоксидный + Foul Release (силиконовый, пресная вода) | B19: шт. | C19: 1700 | D19: =(978/1.22)*1.039 -> 832.90328 | E19: =C19*D19 -> 1415935.6 | F19: ГК ДЖИФЛЕКС | G19: https://spb.gflex.ru/catalog/gruntovki/3276/?ysclid=muenx18ulq726592891
A20: Грунт + Полиуретановая эмаль (UV-стойкая, КМ1/КМ2) | B20: кг | C20: 8800 | D20: =(2805/1.22)*1.039 -> 2388.8484 | E20: =C20*D20 -> 21021866 | F20: Магазин красок "Колор" | G20: https://color1.ru/antikorrozionnaya-poliuretanova-grunt-emal-indosingl-pu-tsvet-ral-9017-v-komplekte-s-otverditelem-1kg-0-25l
A21: Итого затрат на материалы | E21: =SUM(E5:E20) -> 2.2192336e+08

Sheet ПКИ
A4: Наименование ПКИ | B4: Единица измерения | C4: Количество | D4: Цена за единицу, без НДС | E4: Поставщик | F4: Примечание
A5: Обурудование для дизель- электрического пропульсивного комплекса | B5: шт. | C5: 1 | D5: 67580000 | E5: Weichai Power Co., Ltd. (Marine Division) | F5: См. ТКП №1 в приложении
A6: Гребные колёса и сопутствующее оборудование для судна | B6: шт. | C6: 1 | D6: 13500000 | E6: ООО «Плато-Инжиниринг» | F6: См. ТКП №2 в приложении
A7: Оборудование и арматура общесудовых систем и ситем СЭУ | B7: шт. | C7: 1 | D7: 36800000 | E7: ООО «Промтехнологии» | F7: См. ТКП №3 в приложении
A8: Система вентиляции и кондиционирования воздуха, ООО ХХР | B8: шт. | C8: 1 | D8: 228000000 | E8: ООО "ХХР" | F8: См. ТКП №4 в приложении
A9: Итого затраты на ПКИ | D9: =SUM(D5:D8) -> 345880000

Sheet Расчёт трудоемкости
A2: Расчет общей трудоёмкости ОПР, необходимой для работы на заказе
A4: Этап работ согласно дорожной карте | B4: Расчёт общей трудоёмкости | E4: Распределение по годам, н/ч
B5: Вид работ | C5: Общая трудоемкость (чел/час) | D5: Общая трудоемкость (н/час) | E5: 2027 | F5: 2028 | G5: 2029
A7: 10.1. Корпусообработка, изготовление деталей | B7: Обработка деталей корпуса | C7: 33750 | D7: =33750*1.05 -> 35437.5 | E7: 10839.71 | F7: 24597.79 | G7: -
A8: 10.2. Сборка и сварка секций и блоков | B8: Предварительная сборка конструкций | C8: 81397 | D8: =81397*1.05 -> 85466.85 | E8: 26142.8 | F8: 59324.05 | G8: -
A9: 10.3. Изготовление изделий МСЧ | B9: Изготовление изделий МСЧ | C9: 73456 | D9: =C9*1.05 -> 77128.8 | E9: 16851.67 | F9: 60277.13 | G9: -
A10: 10.4.1. Формирование корпуса на стапеле | B10: Формирование корпуса | C10: 94632 | D10: =94632*1.05 -> 99363.6 | E10: - | F10: 99363.6 | G10: -
A11: 10.4.2. Монтаж механизмов | B11: Механомонтажные работы | C11: 41691 | D11: =41691*1.05 -> 43775.55 | E11: - | F11: 43775.55 | G11: -
A12: 10.4.3. Монтаж трубопроводов | B12: Трубомонтажные работы | C12: 46985 | D12: =46985*1.05 -> 49334.25 | E12: - | F12: 49334.25 | G12: -
A13: 11. Выполнение работ на достроечной набережной | B13: Достроечные работы | C13: 107867 | D13: =107867*1.05 -> 113260.35 | E13: - | F13: 36203.45 | G13: 77056.9
B14: Электромонтажные работы | C14: 52941 | D14: =C14*1.05 -> 55588.05 | E14: - | F14: 17768.61 | G14: 37819.44
A15: 12,14 Испытание кораблей | B15: Испытания судна | C15: 49632 | D15: =49632*1.05 -> 52113.6 | E15: - | F15: - | G15: 52113.6
A16: Итого | C16: =SUM(C7:C15) -> 582351 | D16: =SUM(D7:D15) -> 611468.55 | E16: =SUM(E7:E15) -> 53834.18 | F16: =SUM(F7:F15) -> 390644.43 | G16: =SUM(G7:G15) -> 166989.94

Sheet ФОТ_ОПР_расчёт
A2: Фонд оплаты труда основных производственных рабочих
A4: Вид работ | B4: Трудоемкость, заработная плата, косвенные расходы за 2027-2029 гг.
B5: Общая трудоемкость (н/час) | C5: стоимость 1 н/час, руб.коп. | D5: Основная заработная плата, руб.коп. | E5: Дополнительная заработная плата | G5: Отчисления на социальное страхование | I5: ОПР | K5: ОХР
E6: % | F6: Сумма (руб.коп.) | G6: % | H6: Сумма (руб.коп.) | I6: % | J6: Сумма (руб.коп.) | K6: % | L6: Сумма (руб.коп.)
A7: 2027 год
A8: Обработка деталей корпуса | B8: ='Расчёт трудоемкости'!E7 -> 10839.71 | C8: =1043.15*1.081 -> 1127.6452 | D8: =B8*C8 -> 12223346 | E8: =ДЗП_расчёт!B$10 -> 0.13360324 | F8: =D8*E8 -> 1633078.7 | G8: =Соц_страх_расчёт!C$8 -> 0.328 | H8: =(D8+F8)*G8 -> 4544907.4
A9: Предварительная сборка конструкций | B9: ='Расчёт трудоемкости'!E8 -> 26142.8 | C9: =C8 -> 1127.6452 | D9: =B9*C9 -> 29479802 | E9: =ДЗП_расчёт!B$10 -> 0.13360324 | F9: =D9*E9 -> 3938597 | G9: =Соц_страх_расчёт!C$8 -> 0.328 | H9: =(D9+F9)*G9 -> 10961235
A10: Изготовление изделий МСЧ | B10: ='Расчёт трудоемкости'!E9 -> 16851.67 | C10: =919.97*1.081 -> 994.48757 | D10: =B10*C10 -> 16758776 | E10: =ДЗП_расчёт!B$10 -> 0.13360324 | F10: =D10*E10 -> 2239026.8 | G10: =Соц_страх_расчёт!C$8 -> 0.328 | H10: =(D10+F10)*G10 -> 6231279.4
A11: Итого за 2027 год | B11: =SUM(B8:B10) -> 53834.18 | D11: =SUM(D8:D10) -> 58461924 | F11: =SUM(F8:F10) -> 7810702.4 | H11: =SUM(H8:H10) -> 21737422 | J11: =SUM(J8:J10) -> 0 | L11: =SUM(L8:L10) -> 0
A12: 2028 год
A13: Обработка деталей корпуса | B13: ='Расчёт трудоемкости'!F7 -> 24597.79 | C13: =1043.15*1.155 -> 1204.8383 | D13: =B13*C13 -> 29636358 | E13: =ДЗП_расчёт!B$10 -> 0.13360324 | F13: =D13*E13 -> 3959513.5 | G13: =Соц_страх_расчёт!C$8 -> 0.328 | H13: =(D13+F13)*G13 -> 11019446
A14: Предварительная сборка конструкций | B14: ='Расчёт трудоемкости'!F8 -> 59324.05 | C14: =C13 -> 1204.8383 | D14: =B14*C14 -> 71475885 | E14: =ДЗП_расчёт!B$10 -> 0.13360324 | F14: =D14*E14 -> 9549409.7 | G14: =Соц_страх_расчёт!C$8 -> 0.328 | H14: =(D14+F14)*G14 -> 26576297
A15: Изготовление изделий МСЧ | B15: ='Расчёт трудоемкости'!F9 -> 60277.13 | C15: =919.97*1.155 -> 1062.5654 | D15: =B15*C15 -> 64048390 | E15: =ДЗП_расчёт!B$10 -> 0.13360324 | F15: =D15*E15 -> 8557072.3 | G15: =Соц_страх_расчёт!C$8 -> 0.328 | H15: =(D15+F15)*G15 -> 23814592
A16: Формирование корпуса | B16: ='Расчёт трудоемкости'!F10 -> 99363.6 | C16: =C14 -> 1204.8383 | D16: =B16*C16 -> 1.1971707e+08 | E16: =ДЗП_расчёт!B$10 -> 0.13360324 | F16: =D16*E16 -> 15994588 | G16: =Соц_страх_расчёт!C$8 -> 0.328 | H16: =(D16+F16)*G16 -> 44513422
A17: Механомонтажные работы | B17: ='Расчёт трудоемкости'!F11 -> 43775.55 | C17: =1146.25*1.155 -> 1323.9188 | D17: =B17*C17 -> 57955271 | E17: =ДЗП_расчёт!B$10 -> 0.13360324 | F17: =D17*E17 -> 7743012 | G17: =Соц_страх_расчёт!C$8 -> 0.328 | H17: =(D17+F17)*G17 -> 21549037
A18: Трубомонтажные работы | B18: ='Расчёт трудоемкости'!F12 -> 49334.25 | C18: =C17 -> 1323.9188 | D18: =B18*C18 -> 65314539 | E18: =ДЗП_расчёт!B$10 -> 0.13360324 | F18: =D18*E18 -> 8726233.9 | G18: =Соц_страх_расчёт!C$8 -> 0.328 | H18: =(D18+F18)*G18 -> 24285373
A19: Достроечные работы | B19: ='Расчёт трудоемкости'!F13 -> 36203.45 | C19: =909.05*1.155 -> 1049.9527 | D19: =B19*C19 -> 38011912 | E19: =ДЗП_расчёт!B$10 -> 0.13360324 | F19: =D19*E19 -> 5078514.5 | G19: =Соц_страх_расчёт!C$8 -> 0.328 | H19: =(D19+F19)*G19 -> 14133660
A20: Электромонтажные работы | B20: ='Расчёт трудоемкости'!F14 -> 17768.61 | C20: =979.36*1.155 -> 1131.1608 | D20: =B20*C20 -> 20099155 | E20: =ДЗП_расчёт!B$10 -> 0.13360324 | F20: =D20*E20 -> 2685312.2 | G20: =Соц_страх_расчёт!C$8 -> 0.328 | H20: =(D20+F20)*G20 -> 7473305.3
A21: Итого за 2028 год | B21: =SUM(B13:B20) -> 390644.43 | D21: =SUM(D13:D20) -> 4.6625858e+08 | F21: =SUM(F13:F20) -> 62293656 | H21: =SUM(H13:H20) -> 1.7336513e+08 | J21: =SUM(J13:J20) -> 0 | L21: =SUM(L13:L20) -> 0
A22: 2029 год
A23: Достроечные работы | B23: ='Расчёт трудоемкости'!G13 -> 77056.9 | C23: =921.17*1.235 -> 1137.645 | D23: =B23*C23 -> 87663393 | E23: =ДЗП_расчёт!B$10 -> 0.13360324 | F23: =D23*E23 -> 11712113 | G23: =Соц_страх_расчёт!C$8 -> 0.328 | H23: =(D23+F23)*G23 -> 32595166
A24: Электромонтажные работы | B24: ='Расчёт трудоемкости'!G14 -> 37819.44 | C24: =979.36*1.235 -> 1209.5096 | D24: =B24*C24 -> 45742976 | E24: =ДЗП_расчёт!B$10 -> 0.13360324 | F24: =D24*E24 -> 6111409.7 | G24: =Соц_страх_расчёт!C$8 -> 0.328 | H24: =(D24+F24)*G24 -> 17008238
A25: Испытания судна | B25: ='Расчёт трудоемкости'!G15 -> 52113.6 | C25: =921.45*1.235 -> 1137.9908 | D25: =B25*C25 -> 59304795 | E25: =ДЗП_расчёт!B$10 -> 0.13360324 | F25: =D25*E25 -> 7923312.7 | G25: =Соц_страх_расчёт!C$8 -> 0.328 | H25: =(D25+F25)*G25 -> 22050819
A26: Итого за 2029 год | B26: =SUM(B23:B25) -> 166989.94 | D26: =SUM(D23:D25) -> 1.9271116e+08 | F26: =SUM(F23:F25) -> 25746836 | H26: =SUM(H23:H25) -> 71654224 | J26: =SUM(J23:J25) -> 0 | L26: =SUM(L23:L25) -> 0
A27: ВСЕГО | B27: =B26+B21+B11 -> 611468.55 | D27: =D26+D21+D11 -> 7.1743166e+08 | F27: =F26+F21+F11 -> 95851194 | H27: =H26+H21+H11 -> 2.6675678e+08 | J27: =J26+J21+J11 -> 0 | L27: =L26+L21+L11 -> 0

Sheet ДЗП_расчёт
A3: Структура ДЗП
A4: Наименование | B4: Продолжительность, дни
A5: Ежегодный основной и дополнительный отпуск, предусмотренный законодательством Российской Федерации (без денежной компенсации за неиспользованный отпуск) | B5: 28
A6: Временная нетрудоспособность (больничный лист) работника в соответствии с нормами законодательства РФ | B6: 3 | C6: В среднем, по данным исследований (вставить ссылку)
A7: Время медицинского обследования, дней сдачи крови и ее компонентов и предоставленных в связи с этим дней отдыха | B7: 2 | C7: (в среднем в соответствии с ТК)
A8: Итого | B8: =SUM(B5:B7) -> 33
A9: База распределения - количество рабочих дней | B9: 247
A10: % ДЗП | B10: =B8/B9 -> 0.13360324

Sheet Соц_страх_расчёт
B3: Структура отчислений во внебюджетные фонды | C3: Величина отчислений, % | D3: Примечание
B4: Обязательное пенсионное страхование | C4: 0.22
B5: Обязательное медицинское страхование | C5: 0.051
B6: Обязательное социальное страхование на случай временной нетрудоспособности и в связи с материнством | C6: 0.029
B7: От несчастных случаев на производстве и профзаболеваний | C7: 0.028 | D7: Согл. ОКВЭД
B8: Итого | C8: =SUM(C4:C7) -> 0.328

Sheet АУП_ИТР_расчёт
A1: Наименование должности | B1: Кол-во | C1: База, руб. | D1: Категория персонала | E1: База, руб. | F1: Премия, 10% | G1: Итого основная ЗП | H1: ДЗП | I1: Отчисления во внебюджетные фонды | J1: Итого затраты на оплату труда | K1: Ссылка на вакансию
A2: Зам. главного инженера | B2: 1 | C2: 130000 | D2: АУП | E2: 130000 | F2: =E2*0.1 -> 13000 | G2: =E2+F2 -> 143000 | H2: =G2*ДЗП_расчёт!B$10 -> 19105.263 | I2: =(G2+H2)*Соц_страх_расчёт!C$8 -> 53170.526 | J2: =G2+H2+I2 -> 215275.79 | K2: https://spb.hh.ru/vacancy/136536917?query=заместитель+главного+инженера&hhtmFrom=vacancy_search_list
A3: Ведущий конструктор | B3: 4 | C3: 170000 | D3: ИТР | E3: 680000 | F3: =E3*0.1 -> 68000 | G3: =E3+F3 -> 748000 | H3: =G3*ДЗП_расчёт!B$10 -> 99935.223 | I3: =(G3+H3)*Соц_страх_расчёт!C$8 -> 278122.75 | J3: =G3+H3+I3 -> 1126058 | K3: https://spb.hh.ru/vacancy/137042333?query=ведущий+конструктор&hhtmFrom=vacancy_search_list
A4: Ведущий технолог | B4: 4 | C4: 100000 | D4: ИТР | E4: 400000 | F4: =E4*0.1 -> 40000 | G4: =E4+F4 -> 440000 | H4: =G4*ДЗП_расчёт!B$10 -> 58785.425 | I4: =(G4+H4)*Соц_страх_расчёт!C$8 -> 163601.62 | J4: =G4+H4+I4 -> 662387.04 | K4: https://spb.hh.ru/vacancy/137049104?query=ведущий+технолог&hhtmFrom=vacancy_search_list
A5: Ведущий специалист технического контроля | B5: 3 | C5: 150000 | D5: ИТР | E5: 450000 | F5: =E5*0.1 -> 45000 | G5: =E5+F5 -> 495000 | H5: =G5*ДЗП_расчёт!B$10 -> 66133.603 | I5: =(G5+H5)*Соц_страх_расчёт!C$8 -> 184051.82 | J5: =G5+H5+I5 -> 745185.43 | K5: https://spb.hh.ru/vacancy/135598070?query=ведущий+специалист+технического+контроля&hhtmFrom=vacancy_search_list
A6: Ведущий экономист | B6: 2 | C6: 120000 | D6: АУП | E6: 240000 | F6: =E6*0.1 -> 24000 | G6: =E6+F6 -> 264000 | H6: =G6*ДЗП_расчёт!B$10 -> 35271.255 | I6: =(G6+H6)*Соц_страх_расчёт!C$8 -> 98160.972 | J6: =G6+H6+I6 -> 397432.23 | K6: https://spb.hh.ru/vacancy/136537115?query=ведущий+экономист&hhtmFrom=vacancy_search_list
A7: Ведущий инженер-технолог | B7: 4 | C7: 150000 | D7: ИТР | E7: 600000 | F7: =E7*0.1 -> 60000 | G7: =E7+F7 -> 660000 | H7: =G7*ДЗП_расчёт!B$10 -> 88178.138 | I7: =(G7+H7)*Соц_страх_расчёт!C$8 -> 245402.43 | J7: =G7+H7+I7 -> 993580.57 | K7: https://spb.hh.ru/vacancy/137482925?query=ведущий+инженер-технолог&hhtmFrom=vacancy_search_list
A8: Инженер - конструктор 1 кат. | B8: 4 | C8: 150000 | D8: ИТР | E8: 600000 | F8: =E8*0.1 -> 60000 | G8: =E8+F8 -> 660000 | H8: =G8*ДЗП_расчёт!B$10 -> 88178.138 | I8: =(G8+H8)*Соц_страх_расчёт!C$8 -> 245402.43 | J8: =G8+H8+I8 -> 993580.57 | K8: https://spb.hh.ru/vacancy/136907155?query=инженер-конструктор+1+категории&hhtmFrom=vacancy_search_list
A9: Технолог 1 кат. | B9: 5 | C9: 120000 | D9: ИТР | E9: 600000 | F9: =E9*0.1 -> 60000 | G9: =E9+F9 -> 660000 | H9: =G9*ДЗП_расчёт!B$10 -> 88178.138 | I9: =(G9+H9)*Соц_страх_расчёт!C$8 -> 245402.43 | J9: =G9+H9+I9 -> 993580.57 | K9: https://spb.hh.ru/vacancy/137572170?query=технолог+1+категории&hhtmFrom=vacancy_search_list
A10: Итого: | B10: =SUM(B2:B9) -> 27 | C10: =SUM(C2:C9) -> 1090000 | E10: =SUM(E2:E9) -> 3700000 | G10: =SUM(G2:G9) -> 4070000 | H10: =SUM(H2:H9) -> 543765.18 | I10: =SUM(I2:I9) -> 1513315 | J10: =SUM(J2:J9) -> 6127080.2
A12: Начальник производства | B12: 1 | C12: 200000 | D12: АУП | E12: 200000 | F12: =E12*0.1 -> 20000 | G12: =E12+F12 -> 220000 | H12: =G12*ДЗП_расчёт!B$10 -> 29392.713 | I12: =(G12+H12)*Соц_страх_расчёт!C$8 -> 81800.81 | J12: =G12+H12+I12 -> 331193.52 | K12: https://spb.hh.ru/vacancy/137711314?query=начальник+производства&hhtmFrom=vacancy_search_list
A13: Начальник участка | B13: 5 | C13: 170000 | D13: ИТР | E13: 850000 | F13: =E13*0.1 -> 85000 | G13: =E13+F13 -> 935000 | H13: =G13*ДЗП_расчёт!B$10 -> 124919.03 | I13: =(G13+H13)*Соц_страх_расчёт!C$8 -> 347653.44 | J13: =G13+H13+I13 -> 1407572.5 | K13: https://spb.hh.ru/vacancy/137569275?query=начальник+участка&hhtmFrom=vacancy_search_list
A14: Старший мастер участка | B14: 7 | C14: 180000 | D14: ИТР | E14: 1260000 | F14: =E14*0.1 -> 126000 | G14: =E14+F14 -> 1386000 | H14: =G14*ДЗП_расчёт!B$10 -> 185174.09 | I14: =(G14+H14)*Соц_страх_расчёт!C$8 -> 515345.1 | J14: =G14+H14+I14 -> 2086519.2 | K14: https://spb.hh.ru/vacancy/136540024?query=старший+мастер+участка&hhtmFrom=vacancy_search_list
A15: Мастер участка | B15: 7 | C15: 130000 | D15: ИТР | E15: 910000 | F15: =E15*0.1 -> 91000 | G15: =E15+F15 -> 1001000 | H15: =G15*ДЗП_расчёт!B$10 -> 133736.84 | I15: =(G15+H15)*Соц_страх_расчёт!C$8 -> 372193.68 | J15: =G15+H15+I15 -> 1506930.5 | K15: https://spb.hh.ru/vacancy/137655586?query=мастер+участка&hhtmFrom=vacancy_search_list
A16: Специалист по охране труда | B16: 2 | C16: 120000 | D16: ИТР | E16: 240000 | F16: =E16*0.1 -> 24000 | G16: =E16+F16 -> 264000 | H16: =G16*ДЗП_расчёт!B$10 -> 35271.255 | I16: =(G16+H16)*Соц_страх_расчёт!C$8 -> 98160.972 | J16: =G16+H16+I16 -> 397432.23 | K16: https://spb.hh.ru/vacancy/137697813?query=специалист+по+охране+труда&hhtmFrom=vacancy_search_list
A17: Специалист по МТО | B17: 2 | C17: 150000 | D17: ИТР | E17: 300000 | F17: =E17*0.1 -> 30000 | G17: =E17+F17 -> 330000 | H17: =G17*ДЗП_расчёт!B$10 -> 44089.069 | I17: =(G17+H17)*Соц_страх_расчёт!C$8 -> 122701.21 | J17: =G17+H17+I17 -> 496790.28 | K17: https://spb.hh.ru/vacancy/137355491?query=специалист+по+МТО&hhtmFrom=vacancy_search_list
A18: Наладчик системы | B18: 10 | C18: 100000 | D18: ИТР | E18: 1000000 | F18: =E18*0.1 -> 100000 | G18: =E18+F18 -> 1100000 | H18: =G18*ДЗП_расчёт!B$10 -> 146963.56 | I18: =(G18+H18)*Соц_страх_расчёт!C$8 -> 409004.05 | J18: =G18+H18+I18 -> 1655967.6 | K18: https://spb.hh.ru/vacancy/136953728?query=наладчик+системы&hhtmFrom=vacancy_search_list
A19: Кладовщик | B19: 7 | C19: 75000 | D19: ВПР | E19: 525000 | F19: =E19*0.1 -> 52500 | G19: =E19+F19 -> 577500 | H19: =G19*ДЗП_расчёт!B$10 -> 77155.87 | I19: =(G19+H19)*Соц_страх_расчёт!C$8 -> 214727.13 | J19: =G19+H19+I19 -> 869383 | K19: https://spb.hh.ru/vacancy/137709749?query=кладовщик+на+завод&hhtmFrom=vacancy_search_list
A20: Специалист по связям с общественностью | B20: 2 | C20: 80000 | D20: РСИС | E20: 160000 | F20: =E20*0.1 -> 16000 | G20: =E20+F20 -> 176000 | H20: =G20*ДЗП_расчёт!B$10 -> 23514.17 | I20: =(G20+H20)*Соц_страх_расчёт!C$8 -> 65440.648 | J20: =G20+H20+I20 -> 264954.82 | K20: https://spb.hh.ru/vacancy/132322232?query=специалист+по+связям+с+общественностью&hhtmFrom=vacancy_search_list
A21: Строитель кораблей | B21: 7 | C21: 120000 | D21: ИТР | E21: 840000 | F21: =E21*0.1 -> 84000 | G21: =E21+F21 -> 924000 | H21: =G21*ДЗП_расчёт!B$10 -> 123449.39 | I21: =(G21+H21)*Соц_страх_расчёт!C$8 -> 343563.4 | J21: =G21+H21+I21 -> 1391012.8 | K21: https://spb.hh.ru/search/vacancy?text=главный+строитель+кораблей&salary=&ored_clusters=true&area=2&suggestId=5f773725-bec5-4e17-8e9c-57afa341078d&hhtmFrom=vacancy_search_list&hhtmFromLabel=vacancy_search_line
A22: Итого: | B22: =SUM(B12:B21) -> 50 | C22: =SUM(C12:C21) -> 1325000 | E22: =SUM(E12:E21) -> 6285000 | G22: =SUM(G12:G21) -> 6913500 | H22: =SUM(H12:H21) -> 923665.99 | I22: =SUM(I12:I21) -> 2570590.4 | J22: =SUM(J12:J21) -> 10407756
A23: Всего затрат на АУП | J23: =J22+J10 -> 16534837

Sheet Обязательное обучение
B3: Обучающая организация | C3: Тема обучения | D3: стоимость обучения за 1 чел | E3: Кол-во сотрудников | F3: Итого:
B4: АНО ДПО «Учебный центр «Перспектива» | C4: Организация деятельности и эксплуатации электроустановок для производства испытаний (измерений)-электролабораторий | D4: =4200*1.04 -> 4368 | E4: 30 | F4: =D4*E4 -> 131040
B5: АНО ДПО «Прикамский институт безопасности | C5: Поверка и калибровка средств измерений теплотехнических величин (давления, расхода, температуры) 108 часов | D5: =8000*1.04 -> 8320 | E5: 15 | F5: =D5*E5 -> 124800
B6: АНО ДПО «ДВИПРАЗ» | C6: Поверка и калибровка средств геометрических измерений | D6: =526*1.04 -> 547.04 | E6: 25 | F6: =D6*E6 -> 13676
B7: ЧОУ ДПО "Учебный центр "Конфакт" | C7: Повторная проверка знаний машиниста плавучего крана. | D7: =2000*1.04 -> 2080 | E7: 35 | F7: =D7*E7 -> 72800
B8: ЧОУ ДПО "Морские системы" | C8: Подготовка в соответствии с требованиями пунктов 1-4 Раздела А-VI/I кодекса ПДНВ | D8: =7300*1.04 -> 7592 | E8: 20 | F8: =D8*E8 -> 151840
B9: ООО Многофункциональный Учебно-Информационный Центр "Меркурий" | C9: Специалист по пожарной профилактике | D9: =350*1.04 -> 364 | E9: 100 | F9: =D9*E9 -> 36400
B10: ЧОУ ДПО "Спутник" | C10: Техносферная безопасность. Охрана труда | D10: =808*1.04 -> 840.32 | E10: 150 | F10: =D10*E10 -> 126048
B11: ЧОУ ДПО "Морские системы" | C11: Подготовка специалиста по спасательным шлюпкам и плотам и дежурным шлюпкам, не являющимся скоростными дежурными шлюпками, в соответствии с пунктами 1-4 раздела A-VI/2 Кодекса ПДНВ (Пункт 1.3 Правила VI/2 Конвенции ПДНВ) (первично) | D11: =3000*1.04 -> 3120 | E11: 30 | F11: =D11*E11 -> 93600
B12: ИП Климчук В.А. | C12: Обучение по охране труда | D12: =376800*1.04 -> 391872 | E12: общий договор | F12: =D12 -> 391872
B13: ИП Лысенко И.М. | C13: Обучение по электробезопасности | D13: =178020*1.041 -> 185318.82 | E13: общий договор | F13: =D13 -> 185318.82
B14: АНО ДПО "ПРОФАТОМЭНЕРГО" | C14: Обучение по радиационной безопасности | D14: =306360*1.04 -> 318614.4 | E14: общий договор | F14: =D14 -> 318614.4
B15: Итого затраты на обязательное обучение | D15: =SUM(D4:D14) -> 923036.58 | F15: =SUM(F4:F14) -> 1646009.2

Sheet Маркетинг
A2: Поставшик | B2: Варианты рекламы | C2: Стоимость руб./месяц | D2: Источник
A3: Метроплитен СПБ | B3: Реклама на щитах 4×2 м | C3: 124000 | D3: Макет будет выполнен дизайнером отдела по связям с общественность АО "Адмиралтейские верфи" https://www.metro-spb.ru/reklama-na-stanciyah-metro/shchit-putevoj.htm?ysclid=mudu3rg6be486653059
A4: АО "Адмиралтейские верфи" | B4: Буклеты, раздаточная продукция | C4: 3000 | D4: Печать будет осуществляться в типографии предприятия из расчета 30 рублей за буклет А4, цветная печать с двух сторон, в количестве 100 штук. Буклеты будут раздаваться силами работников на профориетационных и других рекламных мероприятиях (Конференциях, Выставках и т.д.)
A5: АО "Адмиралтейские верфи" | B5: Реклама в социальных сетях | C5: 0 | D5: АО "Адмиралтейские верфи" ведут несколько социальных сетей на разных площадках: Телеграм, Макс, Вконтакте силами сотрудников предприятия
A6: Итого затраты на маркетинг и продвижение за год | C6: =SUM(C3:C5)*12 -> 1524000

Sheet ОПР_Расчет
A4: 01.10 - Материалы
A5: 01.22 - Расходы на приобретение, изготовление и ремонт инструмента, инвентаря
A6: 01.23 - Расходы на ГСМ и топливо
A7: 01.25 - Расходы на сварочное оборудование, расходные и комплектующие материалы
A8: 01.27 - Прочие расходы обеспечивающие охрану труда (мыло, защитные средства и прочее)
A9: 01.29 - Расходы на мебель
A10: 01.30 - Расходы на МБП не производственного характера
A11: 02.11.в - Расходы на обеспечение цехов энергетическими услугами на технологические цели (вода)
A12: 02.11.г - Расходы на обеспечение цехов энергетическими услугами на технологические цели (газы)
A13: 02.11.с - Расходы на обеспечение цехов энергетическими услугами на технологические цели (стоки)
A14: 02.11.т - Расходы на обеспечение цехов энергетическими услугами на технологические цели (тепло)
A15: 02.11.э - Расходы на обеспечение цехов энергетическими услугами на технологические цели (электричество)
... A39: 14.39 - Экспертизы, поверки и прочее

Sheet ОХР_Расчет
A4: Оплата труда персоналу общехозяйственного назначения
A5: Страховые взносы с оплаты труда персонала общехозяйственного назанчения
A6: 01.23 - Расходы на ГСМ и топливо
A7: 01.31 - Прочие материалы
A8: 01.32 - Расходы на спец. одежду и средства индивидуальной защиты
A9: 01.33 - Расходы на инструмент и прочие приспособления
A10: 01.34 - Расходы на оргтехнику, ремонт и содержание
A11: 11.12 - Амортизация ОС, НМА
A12: 17.10 - Аренда и лизинг
A13: 17.11в - Расходы на обеспечение общества энергетическими услугами (вода)
A14: 17.11с - Расходы на обеспечение общества энергетическими услугами (стоки)
A15: 17.11т - Расходы на обеспечение общества энергетическими услугами (тепло)
... A53: 79… - Расходы отдельных подразделений вспомогательного производства, связанные с работами инженерно-технического обслуживания основного производства продукции, работ (услуг) АО "Адмиралтейские верфи"

Sheet Точка безубыточности
