Workbook

Sheet Калькуляция
A1: Калькуляция себестоимости и цены головного судна, руб.
A3: Статья | B3: Всего | C3: 2027 | D3: 2028 | E3: 2029 | F3: Примечание
A4: Материальные затраты | B4: =SUM(C4:E4) -> 5.8696224e+08 | C4: =C5+C6+C7 -> 5.8696224e+08 | D4: =D5+D6+D7 -> 0 | E4: =E5+E6+E7 -> 0
A5: сырьё, материалы, вспомогательные материалы | B5: =SUM(C5:E5) -> 2.2780868e+08 | C5: =Материалы!$H$20 -> 2.2780868e+08 | D5: 0 | E5: 0 | F5: закупка по договорам 2027 года
A6: покупные комплектующие изделия | B6: =SUM(C6:E6) -> 3.5276722e+08 | C6: =ПКИ!$E$9 -> 3.5276722e+08 | D6: 0 | E6: 0 | F6: технико-коммерческие предложения
A7: транспортно-заготовительные расходы | B7: =SUM(C7:E7) -> 6386334.9 | C7: =(C5+C6)*Исходные!$B$5 -> 6386334.9 | D7: 0 | E7: 0
A8: Затраты на оплату труда | B8: =SUM(C8:E8) -> 8.1668353e+08 | C8: =C9+C10 -> 67424018 | D8: =D9+D10 -> 4.5821886e+08 | E8: =E9+E10 -> 2.9104066e+08
A9: основная заработная плата | B9: =SUM(C9:E9) -> 7.2043155e+08 | C9: =ФОТ!G22 -> 59477616 | D9: =ФОТ!G23 -> 4.0421449e+08 | E9: =ФОТ!G24 -> 2.5673944e+08
A10: дополнительная заработная плата | B10: =SUM(C10:E10) -> 96251988 | C10: =ФОТ!H22 -> 7946402.1 | D10: =ФОТ!H23 -> 54004365 | E10: =ФОТ!H24 -> 34301221
A11: Страховые взносы | B11: =SUM(C11:E11) -> 2.678722e+08 | C11: =ФОТ!I22 -> 22115078 | D11: =ФОТ!I23 -> 1.5029579e+08 | E11: =ФОТ!I24 -> 95461336
A12: Общепроизводственные затраты | B12: =SUM(C12:E12) -> 3.2568553e+08 | C12: ='АУП и ИТР'!M24+Обучение!$G$15 -> 30101499 | D12: ='АУП и ИТР'!N24 -> 1.4085632e+08 | E12: ='АУП и ИТР'!O24 -> 1.5472771e+08 | F12: руководство производством, обучение
A13: Общехозяйственные затраты | B13: =SUM(C13:E13) -> 2.08584e+08 | C13: ='АУП и ИТР'!M25 -> 30027121 | D13: ='АУП и ИТР'!N25 -> 85088719 | E13: ='АУП и ИТР'!O25 -> 93468165 | F13: инженерная и управленческая группа
A14: Производственная себестоимость | B14: =SUM(C14:E14) -> 2.2057875e+09 | C14: =C4+C8+C11+C12+C13 -> 7.3662995e+08 | D14: =D4+D8+D11+D12+D13 -> 8.3445969e+08 | E14: =E4+E8+E11+E12+E13 -> 6.3469787e+08
A15: Коммерческие расходы | B15: =SUM(C15:E15) -> 15040907 | C15: ='АУП и ИТР'!M26+Маркетинг!C10 -> 4223798.5 | D15: ='АУП и ИТР'!N26+Маркетинг!C11 -> 5206516.1 | E15: ='АУП и ИТР'!O26+Маркетинг!C12 -> 5610592 | F15: маркетинг, связи с общественностью
A16: Полная себестоимость | B16: =SUM(C16:E16) -> 2.2208284e+09 | C16: =C14+C15 -> 7.4085375e+08 | D16: =D14+D15 -> 8.396662e+08 | E16: =E14+E15 -> 6.4030846e+08
A17: Прибыль | B17: =B16*Исходные!$B$13 -> 3.3312426e+08 | F17: рентабельность к полной себестоимости
A18: Цена судна без НДС | B18: =B16+B17 -> 2.5539527e+09
A19: НДС | B19: =B18*Исходные!$B$4 -> 5.6186959e+08
A20: Цена судна с НДС | B20: =B18+B19 -> 3.1158223e+09
A21: Трудоёмкость, н·ч | B21: =SUM(C21:E21) -> 611469 | C21: =Трудоёмкость!G13 -> 54764.969 | D21: =Трудоёмкость!H13 -> 343628.95 | E21: =Трудоёмкость!I13 -> 213075.08

Sheet Исходные
A1: Исходные данные расчёта
A3: Параметр | B3: Значение | C3: Ед. | D3: Основание
A4: НДС | B4: 0.22 | C4: % | D4: с 2026 года
A5: Транспортно-заготовительные расходы от материалов и ПКИ | B5: 0.011 | C5: % | D5: норматив верфи
A6: Коэффициент использования металла | B6: 0.85 | D6: корпус и надстройка, 0,80…0,90
A7: Масса корпуса металлического, сталь D36 | B7: 806.6 | C7: т | D7: нагрузка масс проекта
A8: Масса надстройки и рубки, АМг5 | B8: 136.3 | C8: т | D8: нагрузка масс проекта
A9: Коэффициент выполнения норм | B9: 1.05 | D9: Приказ Минпромторга № 822
A10: Коэффициент головного судна к серийному | B10: 1.3 | D10: Приказ Минпромторга № 958, прил. 7
A11: Премия АУП и ИТР к окладу | B11: 0.1 | C11: % | D11: положение об оплате труда
A12: Фонд рабочего времени в месяц | B12: 164.66667 | C12: ч | D12: 247 рабочих дней × 8 ч / 12
A13: Рентабельность к полной себестоимости | B13: 0.15 | C13: % | D13: принята для гражданского судна
A14: Ставка дисконтирования | B14: 0.15 | C14: % | D14: ключевая ставка Банка России с премией за риск
A15: Серийных судов после головного, по одному в год | B15: 5 | C15: шт. | D15: рынок принимает до 21 судна
A16: Рост цен после 2029 года | B16: 0.06 | C16: % в год | D16: прогноз инфляции
A17: Индекс цен и оплаты труда 2026 | B17: 1 | D17: базовый год
A18: Индекс цен и оплаты труда 2027 | B18: 1.081 | D18: прогноз
A19: Индекс цен и оплаты труда 2028 | B19: 1.155 | D19: прогноз
A20: Индекс цен и оплаты труда 2029 | B20: 1.235 | D20: прогноз

Sheet ДЗП
A1: Дополнительная заработная плата
A3: Наименование | B3: Дней в году
A4: Ежегодный основной и дополнительный отпуск | B4: 28
A5: Временная нетрудоспособность | B5: 3
A6: Медицинское обследование, донорские дни и отдых после них | B6: 2
A7: Итого | B7: =SUM(B4:B6) -> 33
A8: База - рабочих дней в году | B8: 247
A9: ДЗП к основной заработной плате | B9: =B7/B8 -> 0.13360324

Sheet Взносы
A1: Страховые взносы
A3: Вид страхования | B3: Ставка
A4: Обязательное пенсионное страхование | B4: 0.22
A5: Обязательное медицинское страхование | B5: 0.051
A6: Временная нетрудоспособность и материнство | B6: 0.029
A7: От несчастных случаев на производстве и профзаболеваний, по ОКВЭД | B7: 0.028
A8: Итого | B8: =SUM(B4:B7) -> 0.328

Sheet Материалы
A1: Сырьё, материалы и вспомогательные материалы
A3: Наименование | B3: Ед. | C3: Количество | D3: Доля в группе | E3: Цена за ед. с НДС, 2026 | F3: Индекс к 2027 | G3: Цена за ед. без НДС, 2027 | H3: Сумма, руб. | I3: Поставщик | J3: Сайт
A4: Лист судостроительный 10×1600×6000, категория D36 | B4: т | C4: =Исходные!$B$7/Исходные!$B$6*D4 -> 521.04923 | D4: 0.54908486 | E4: 70000 | F4: 1.052 | G4: =E4/(1+Исходные!$B$4)*F4 -> 60360.656 | H4: =C4*G4 -> 31450873 | I4: АО «Металлсервис» | J4: mc.ru
A5: Лист стальной 24×2000×6000, D36 ГОСТ Р 52927-2015 | B5: т | C5: =Исходные!$B$7/Исходные!$B$6*D5 -> 43.420769 | D5: 0.045757072 | E5: 45011 | F5: 1.052 | G5: =E5/(1+Исходные!$B$4)*F5 -> 38812.764 | H5: =C5*G5 -> 1685280.1 | I5: торговая площадка «Пульс цен» | J5: pulscen.ru
A6: Лист низколегированный 6×1500×6000, 09Г2С-15 | B6: т | C6: =Исходные!$B$7/Исходные!$B$6*D6 -> 199.73554 | D6: 0.21048253 | E6: 70990 | F6: 1.052 | G6: =E6/(1+Исходные!$B$4)*F6 -> 61214.328 | H6: =C6*G6 -> 12226677 | I6: АО «Металлсервис» | J6: mc.ru
A7: Швеллер 12П, 09Г2С-15, длина 12 м | B7: т | C7: =Исходные!$B$7/Исходные!$B$6*D7 -> 184.73564 | D7: 0.19467554 | E7: 112490 | F7: 1.052 | G7: =E7/(1+Исходные!$B$4)*F7 -> 96999.574 | H7: =C7*G7 -> 17919278 | I7: АО «Металлсервис» | J7: mc.ru
A8: Лист АМг5М 6×1500×4000 | B8: т | C8: =Исходные!$B$8/Исходные!$B$6*D8 -> 129.47753 | D8: 0.80745342 | E8: 700000 | F8: 1.043 | G8: =E8/(1+Исходные!$B$4)*F8 -> 598442.62 | H8: =C8*G8 -> 77484873 | I8: ООО «Невская Алюминиевая Компания» | J8: spbalum.ru
A9: Тавр АМг5 20×20×2 ГОСТ 13622-91 | B9: т | C9: =Исходные!$B$8/Исходные!$B$6*D9 -> 22.907563 | D9: 0.14285714 | E9: 296060 | F9: 1.052 | G9: =E9/(1+Исходные!$B$4)*F9 -> 255291.08 | H9: =C9*G9 -> 5848096.5 | I9: «Металл-союз» | J9: metsklad.ru
A10: Уголок АМг5 50×30×3 | B10: т | C10: =Исходные!$B$8/Исходные!$B$6*D10 -> 4.7807088 | D10: 0.029813665 | E10: 1600000 | F10: 1.052 | G10: =E10/(1+Исходные!$B$4)*F10 -> 1379672.1 | H10: =C10*G10 -> 6595810.7 | I10: ПКФ «Металл СВ» | J10: sv-metal.ru
A11: Уголок АМг5 40×25×4 | B11: т | C11: =Исходные!$B$8/Исходные!$B$6*D11 -> 3.1871392 | D11: 0.019875776 | E11: 408500 | F11: 1.052 | G11: =E11/(1+Исходные!$B$4)*F11 -> 352247.54 | H11: =C11*G11 -> 1122661.9 | I11: Компания «Мост» | J11: moststal.ru
A12: Труба бесшовная DN40…DN125, Ст20 и 09Г2С, ГОСТ 8732 | B12: т | C12: 75.4 | E12: 158870 | F12: 1.04 | G12: =E12/(1+Исходные!$B$4)*F12 -> 135430.16 | H12: =C12*G12 -> 10211434 | I12: ООО МК «Буран» | J12: buranmetall.ru
A13: Труба бесшовная DN20…DN80, 12Х18Н10Т | B13: т | C13: 38.1 | E13: 811000 | F13: 1.04 | G13: =E13/(1+Исходные!$B$4)*F13 -> 691344.26 | H13: =C13*G13 -> 26340216 | I13: ООО ТК «ИноксМаркет» | J13: inoxmarket.ru
A14: Труба ПНД и ПП DN50…DN225, судовая негорючая | B14: км | C14: 8.9 | E14: 205000 | F14: 1.04 | G14: =E14/(1+Исходные!$B$4)*F14 -> 174754.1 | H14: =C14*G14 -> 1555311.5 | I14: компания «Энерго Пайп» | J14: energo-pipe.ru
A15: Судовая арматура, фланцы, клапаны с уплотнением PTFE для метанола | B15: шт. | C15: 50 | E15: 12684 | F15: 1.042 | G15: =E15/(1+Исходные!$B$4)*F15 -> 10833.384 | H15: =C15*G15 -> 541669.18 | I15: ООО «ТД Ватервальве» | J15: shop-watervalve.ru
A16: Кабель силовой, контрольный, огнестойкий, слаботочный | B16: км | C16: 55 | E16: 49800 | F16: 1.042 | G16: =E16/(1+Исходные!$B$4)*F16 -> 42534.098 | H16: =C16*G16 -> 2339375.4 | I16: ООО «СнабКабель» | J16: snabcable.ru
A17: Кабельные трассы (лотки), сальники, проходки | B17: км | C17: 25 | E17: 470640 | F17: 1.042 | G17: =E17/(1+Исходные!$B$4)*F17 -> 401972.85 | H17: =C17*G17 -> 10049321 | I17: АО «ДКС» | J17: dkc.ru
A18: Грунт эпоксидный и покрытие Foul Release для пресной воды | B18: компл. | C18: 1700 | E18: 978 | F18: 1.039 | G18: =E18/(1+Исходные!$B$4)*F18 -> 832.90328 | H18: =C18*G18 -> 1415935.6 | I18: ГК «ДЖИФЛЕКС» | J18: gflex.ru
A19: Грунт и полиуретановая эмаль, стойкая к УФ | B19: кг | C19: 8800 | E19: 2805 | F19: 1.039 | G19: =E19/(1+Исходные!$B$4)*F19 -> 2388.8484 | H19: =C19*G19 -> 21021866 | I19: магазин красок «Колор» | J19: color1.ru
A20: Итого материалы | H20: =SUM(H4:H19) -> 2.2780868e+08

Sheet ПКИ
A1: Покупные комплектующие изделия
A3: Наименование | B3: Ед. | C3: Кол. | D3: Цена за ед. без НДС, руб. | E3: Сумма, руб. | F3: Поставщик | G3: Основание
A4: Оборудование дизель-электрического комплекса - три двухтопливных дизель-генератора 600 кВт (дизель, метанол), ГРЩ, гребные электродвигатели колёс 2 × 550 кВт, преобразователи | B4: компл. | C4: 1 | D4: 67580000 | E4: =C4*D4 -> 67580000 | F4: Weichai Power Co., Ltd. (Marine Division) | G4: ТКП № 1
A5: Гребные колёса с механизмом поворота плиц и сопутствующее оборудование | B5: компл. | C5: 1 | D5: 13500000 | E5: =C5*D5 -> 13500000 | F5: ООО «Плато-Инжиниринг» | G5: ТКП № 2
A6: Оборудование и арматура общесудовых систем и систем СЭУ | B6: компл. | C6: 1 | D6: 36800000 | E6: =C6*D6 -> 36800000 | F6: ООО «Промтехнологии» | G6: ТКП № 3
A7: Система вентиляции и кондиционирования воздуха | B7: компл. | C7: 1 | D7: 228000000 | E7: =C7*D7 -> 228000000 | F7: поставщик по ТКП № 4 | G7: ТКП № 4
A8: Фундаменты-замки модулей солнечной палубы ВГ-2026.46.00 (твистлок «ласточкин хвост»), с ЗИП и испытаниями | B8: шт. | C8: 72 | D8: 95655.88 | E8: =C8*D8 -> 6887223.4 | F8: цех узла верфи | G8: себестоимость узла
A9: Итого ПКИ | E9: =SUM(E4:E8) -> 3.5276722e+08

Sheet Трудоёмкость
A1: Трудоёмкость постройки головного судна
A3: Вид работ | B3: Трудоёмкость, чел·ч | C3: Трудоёмкость, н·ч | D3: Доля 2027 | E3: Доля 2028 | F3: Доля 2029 | G3: н·ч 2027 | H3: н·ч 2028 | I3: н·ч 2029 | J3: Задачи дорожной карты
A4: Обработка деталей корпуса | B4: 33749.912 | C4: =B4*Исходные!$B$9 -> 35437.408 | D4: 0.31147541 | E4: 0.68852459 | F4: 0 | G4: =C4*D4 -> 11037.881 | H4: =C4*E4 -> 24399.527 | I4: =C4*F4 -> 0 | J4: 10.1. Корпусообработка, изготовление деталей
A5: Предварительная сборка конструкций | B5: 81396.847 | C5: =B5*Исходные!$B$9 -> 85466.689 | D5: 0.31147541 | E5: 0.68852459 | F5: 0 | G5: =C5*D5 -> 26620.772 | H5: =C5*E5 -> 58845.917 | I5: =C5*F5 -> 0 | J5: 10.2. Сборка и сварка секций и блоков
A6: Формирование корпуса на стапеле | B6: 94632.107 | C6: =B6*Исходные!$B$9 -> 99363.712 | D6: 0 | E6: 1 | F6: 0 | G6: =C6*D6 -> 0 | H6: =C6*E6 -> 99363.712 | I6: =C6*F6 -> 0 | J6: 10.4.1. Формирование корпуса на стапеле
A7: Трубомонтажные работы | B7: 46985.172 | C7: =B7*Исходные!$B$9 -> 49334.431 | D7: 0 | E7: 0.50737463 | F7: 0.49262537 | G7: =C7*D7 -> 0 | H7: =C7*E7 -> 25031.038 | I7: =C7*F7 -> 24303.392 | J7: 10.4.3. Монтаж трубопроводов, 11. Работы на достроечной набережной (монтаж оборудования и систем, отделка), пуско-наладочные работы
A8: Механомонтажные работы | B8: 41691.068 | C8: =B8*Исходные!$B$9 -> 43775.621 | D8: 0 | E8: 0.50737463 | F8: 0.49262537 | G8: =C8*D8 -> 0 | H8: =C8*E8 -> 22210.64 | I8: =C8*F8 -> 21564.982 | J8: 10.4.2. Монтаж механизмов, 11. Работы на достроечной набережной (монтаж оборудования и систем, отделка), пуско-наладочные работы
A9: Достроечные работы | B9: 107867.37 | C9: =B9*Исходные!$B$9 -> 113260.73 | D9: 0 | E9: 0.31836735 | F9: 0.68163265 | G9: =C9*D9 -> 0 | H9: =C9*E9 -> 36058.52 | I9: =C9*F9 -> 77202.215 | J9: 11. Работы на достроечной набережной (монтаж оборудования и систем, отделка), пуско-наладочные работы
A10: Испытания судна | B10: 49632.224 | C10: =B10*Исходные!$B$9 -> 52113.835 | D10: 0 | E10: 0 | F10: 1 | G10: =C10*D10 -> 0 | H10: =C10*E10 -> 0 | I10: =C10*F10 -> 52113.835 | J10: 12. Швартовные испытания, 13. Устранение ошибок по результатам швартовных испытаний, 14. Заводские ходовые испытания, 15. Устранение ошибок по результатам заводских ходовых испытаний
A11: Изготовление изделий МСЧ | B11: 73455.691 | C11: =B11*Исходные!$B$9 -> 77128.476 | D11: 0.22178988 | E11: 0.77821012 | F11: 0 | G11: =C11*D11 -> 17106.316 | H11: =C11*E11 -> 60022.16 | I11: =C11*F11 -> 0 | J11: 10.3. Изготовление изделий МСЧ
A12: Электромонтажные работы | B12: 52941.039 | C12: =B12*Исходные!$B$9 -> 55588.091 | D12: 0 | E12: 0.31836735 | F12: 0.68163265 | G12: =C12*D12 -> 0 | H12: =C12*E12 -> 17697.433 | I12: =C12*F12 -> 37890.658 | J12: 11. Работы на достроечной набережной (монтаж оборудования и систем, отделка), пуско-наладочные работы
A13: Итого | B13: =SUM(B4:B12) -> 582351.43 | C13: =SUM(C4:C12) -> 611469 | G13: =SUM(G4:G12) -> 54764.969 | H13: =SUM(H4:H12) -> 343628.95 | I13: =SUM(I4:I12) -> 213075.08
A15: Трудоёмкость по Приказу Минпромторга № 958 на водоизмещение порожнем, чел·ч × коэффициент выполнения норм = нормо-часы. Доли по годам - по рабочим дням задач дорожной карты.

Sheet ФОТ
A1: Фонд оплаты труда основных производственных рабочих
A3: Год | B3: Вид работ | C3: н·ч | D3: Стоимость н·ч 2026, руб. | E3: Индекс | F3: Стоимость н·ч, руб. | G3: Основная ЗП, руб. | H3: ДЗП, руб. | I3: Взносы, руб.
A4: 2027 | B4: Обработка деталей корпуса | C4: =Трудоёмкость!G4 -> 11037.881 | D4: 1043.15 | E4: =Исходные!$B$18 -> 1.081 | F4: =D4*E4 -> 1127.6452 | G4: =C4*F4 -> 12446813 | H4: =G4*ДЗП!$B$9 -> 1662934.5 | I4: =(G4+H4)*Взносы!$B$8 -> 4627997.2
A5: 2027 | B5: Предварительная сборка конструкций | C5: =Трудоёмкость!G5 -> 26620.772 | D5: 1043.15 | E5: =Исходные!$B$18 -> 1.081 | F5: =D5*E5 -> 1127.6452 | G5: =C5*F5 -> 30018785 | H5: =G5*ДЗП!$B$9 -> 4010606.8 | I5: =(G5+H5)*Взносы!$B$8 -> 11161640
A6: 2027 | B6: Изготовление изделий МСЧ | C6: =Трудоёмкость!G11 -> 17106.316 | D6: 919.97 | E6: =Исходные!$B$18 -> 1.081 | F6: =D6*E6 -> 994.48757 | G6: =C6*F6 -> 17012018 | H6: =G6*ДЗП!$B$9 -> 2272860.7 | I6: =(G6+H6)*Взносы!$B$8 -> 6325440.3
A7: 2028 | B7: Обработка деталей корпуса | C7: =Трудоёмкость!H4 -> 24399.527 | D7: 1043.15 | E7: =Исходные!$B$19 -> 1.155 | F7: =D7*E7 -> 1204.8383 | G7: =C7*F7 -> 29397483 | H7: =G7*ДЗП!$B$9 -> 3927598.9 | I7: =(G7+H7)*Взносы!$B$8 -> 10930627
A8: 2028 | B8: Предварительная сборка конструкций | C8: =Трудоёмкость!H5 -> 58845.917 | D8: 1043.15 | E8: =Исходные!$B$19 -> 1.155 | F8: =D8*E8 -> 1204.8383 | G8: =C8*F8 -> 70899812 | H8: =G8*ДЗП!$B$9 -> 9472444.5 | I8: =(G8+H8)*Взносы!$B$8 -> 26362100
A9: 2028 | B9: Формирование корпуса на стапеле | C9: =Трудоёмкость!H6 -> 99363.712 | D9: 1043.15 | E9: =Исходные!$B$19 -> 1.155 | F9: =D9*E9 -> 1204.8383 | G9: =C9*F9 -> 1.197172e+08 | H9: =G9*ДЗП!$B$9 -> 15994606 | I9: =(G9+H9)*Взносы!$B$8 -> 44513473
A10: 2028 | B10: Трубомонтажные работы | C10: =Трудоёмкость!H7 -> 25031.038 | D10: 1146.25 | E10: =Исходные!$B$19 -> 1.155 | F10: =D10*E10 -> 1323.9188 | G10: =C10*F10 -> 33139061 | H10: =G10*ДЗП!$B$9 -> 4427485.9 | I10: =(G10+H10)*Взносы!$B$8 -> 12321827
A11: 2028 | B11: Механомонтажные работы | C11: =Трудоёмкость!H8 -> 22210.64 | D11: 1146.25 | E11: =Исходные!$B$19 -> 1.155 | F11: =D11*E11 -> 1323.9188 | G11: =C11*F11 -> 29405082 | H11: =G11*ДЗП!$B$9 -> 3928614.3 | I11: =(G11+H11)*Взносы!$B$8 -> 10933453
A12: 2028 | B12: Достроечные работы | C12: =Трудоёмкость!H9 -> 36058.52 | D12: 909.05 | E12: =Исходные!$B$19 -> 1.155 | F12: =D12*E12 -> 1049.9527 | G12: =C12*F12 -> 37859742 | H12: =G12*ДЗП!$B$9 -> 5058184.1 | I12: =(G12+H12)*Взносы!$B$8 -> 14077080
A13: 2028 | B13: Изготовление изделий МСЧ | C13: =Трудоёмкость!H11 -> 60022.16 | D13: 919.97 | E13: =Исходные!$B$19 -> 1.155 | F13: =D13*E13 -> 1062.5654 | G13: =C13*F13 -> 63777468 | H13: =G13*ДЗП!$B$9 -> 8520876.2 | I13: =(G13+H13)*Взносы!$B$8 -> 23713857
A14: 2028 | B14: Электромонтажные работы | C14: =Трудоёмкость!H12 -> 17697.433 | D14: 979.36 | E14: =Исходные!$B$19 -> 1.155 | F14: =D14*E14 -> 1131.1608 | G14: =C14*F14 -> 20018642 | H14: =G14*ДЗП!$B$9 -> 2674555.5 | I14: =(G14+H14)*Взносы!$B$8 -> 7443368.9
A15: 2029 | B15: Трубомонтажные работы | C15: =Трудоёмкость!I7 -> 24303.392 | D15: 1146.25 | E15: =Исходные!$B$20 -> 1.235 | F15: =D15*E15 -> 1415.6188 | G15: =C15*F15 -> 34404337 | H15: =G15*ДЗП!$B$9 -> 4596530.9 | I15: =(G15+H15)*Взносы!$B$8 -> 12792285
A16: 2029 | B16: Механомонтажные работы | C16: =Трудоёмкость!I8 -> 21564.982 | D16: 1146.25 | E16: =Исходные!$B$20 -> 1.235 | F16: =D16*E16 -> 1415.6188 | G16: =C16*F16 -> 30527792 | H16: =G16*ДЗП!$B$9 -> 4078611.9 | I16: =(G16+H16)*Взносы!$B$8 -> 11350901
A17: 2029 | B17: Достроечные работы | C17: =Трудоёмкость!I9 -> 77202.215 | D17: 909.05 | E17: =Исходные!$B$20 -> 1.235 | F17: =D17*E17 -> 1122.6768 | G17: =C17*F17 -> 86673132 | H17: =G17*ДЗП!$B$9 -> 11579811 | I17: =(G17+H17)*Взносы!$B$8 -> 32226965
A18: 2029 | B18: Испытания судна | C18: =Трудоёмкость!I10 -> 52113.835 | D18: 921.45 | E18: =Исходные!$B$20 -> 1.235 | F18: =D18*E18 -> 1137.9908 | G18: =C18*F18 -> 59305062 | H18: =G18*ДЗП!$B$9 -> 7923348.4 | I18: =(G18+H18)*Взносы!$B$8 -> 22050919
A19: 2029 | B19: Электромонтажные работы | C19: =Трудоёмкость!I12 -> 37890.658 | D19: 979.36 | E19: =Исходные!$B$20 -> 1.235 | F19: =D19*E19 -> 1209.5096 | G19: =C19*F19 -> 45829114 | H19: =G19*ДЗП!$B$9 -> 6122918.1 | I19: =(G19+H19)*Взносы!$B$8 -> 17040267
A21: Год | B21: Итого | C21: н·ч | G21: Основная ЗП, руб. | H21: ДЗП, руб. | I21: Взносы, руб.
A22: 2027 | B22: Итого за год | C22: =SUMIF($A$4:$A$19,A22,C$4:C$19) -> 54764.969 | G22: =SUMIF($A$4:$A$19,A22,G$4:G$19) -> 59477616 | H22: =SUMIF($A$4:$A$19,A22,H$4:H$19) -> 7946402.1 | I22: =SUMIF($A$4:$A$19,A22,I$4:I$19) -> 22115078
A23: 2028 | B23: Итого за год | C23: =SUMIF($A$4:$A$19,A23,C$4:C$19) -> 343628.95 | G23: =SUMIF($A$4:$A$19,A23,G$4:G$19) -> 4.0421449e+08 | H23: =SUMIF($A$4:$A$19,A23,H$4:H$19) -> 54004365 | I23: =SUMIF($A$4:$A$19,A23,I$4:I$19) -> 1.5029579e+08
A24: 2029 | B24: Итого за год | C24: =SUMIF($A$4:$A$19,A24,C$4:C$19) -> 213075.08 | G24: =SUMIF($A$4:$A$19,A24,G$4:G$19) -> 2.5673944e+08 | H24: =SUMIF($A$4:$A$19,A24,H$4:H$19) -> 34301221 | I24: =SUMIF($A$4:$A$19,A24,I$4:I$19) -> 95461336

Sheet АУП и ИТР
A1: Административно-управленческий персонал и ИТР проекта
A3: Должность | B3: Чел. | C3: Оклад, руб./мес, 2026 | D3: Категория | E3: Статья | F3: Основная ЗП с премией, руб./мес | G3: ДЗП, руб./мес | H3: Взносы, руб./мес | I3: Итого, руб./мес | J3: Месяцев 2027 | K3: Месяцев 2028 | L3: Месяцев 2029 | M3: Затраты 2027, руб. | N3: Затраты 2028, руб. | O3: Затраты 2029, руб.
A4: Заместитель главного инженера | B4: 1 | C4: 130000 | D4: АУП | E4: ОХР | F4: =B4*C4*(1+Исходные!$B$11) -> 143000 | G4: =F4*ДЗП!$B$9 -> 19105.263 | H4: =(F4+G4)*Взносы!$B$8 -> 53170.526 | I4: =F4+G4+H4 -> 215275.79 | J4: 4.5335085 | K4: 12.023653 | L4: 12.352168 | M4: =I4*J4*Исходные!$B$18 -> 1055007 | N4: =I4*K4*Исходные!$B$19 -> 2989603.6 | O4: =I4*L4*Исходные!$B$20 -> 3284016.6
A5: Ведущий конструктор | B5: 4 | C5: 170000 | D5: ИТР | E5: ОХР | F5: =B5*C5*(1+Исходные!$B$11) -> 748000 | G5: =F5*ДЗП!$B$9 -> 99935.223 | H5: =(F5+G5)*Взносы!$B$8 -> 278122.75 | I5: =F5+G5+H5 -> 1126058 | J5: 4.5335085 | K5: 12.023653 | L5: 12.352168 | M5: =I5*J5*Исходные!$B$18 -> 5518497.9 | N5: =I5*K5*Исходные!$B$19 -> 15637927 | O5: =I5*L5*Исходные!$B$20 -> 17177933
A6: Ведущий технолог | B6: 4 | C6: 100000 | D6: ИТР | E6: ОХР | F6: =B6*C6*(1+Исходные!$B$11) -> 440000 | G6: =F6*ДЗП!$B$9 -> 58785.425 | H6: =(F6+G6)*Взносы!$B$8 -> 163601.62 | I6: =F6+G6+H6 -> 662387.04 | J6: 4.5335085 | K6: 12.023653 | L6: 12.352168 | M6: =I6*J6*Исходные!$B$18 -> 3246175.2 | N6: =I6*K6*Исходные!$B$19 -> 9198780.4 | O6: =I6*L6*Исходные!$B$20 -> 10104666
A7: Ведущий специалист технического контроля | B7: 3 | C7: 150000 | D7: ИТР | E7: ОХР | F7: =B7*C7*(1+Исходные!$B$11) -> 495000 | G7: =F7*ДЗП!$B$9 -> 66133.603 | H7: =(F7+G7)*Взносы!$B$8 -> 184051.82 | I7: =F7+G7+H7 -> 745185.43 | J7: 4.5335085 | K7: 12.023653 | L7: 12.352168 | M7: =I7*J7*Исходные!$B$18 -> 3651947.2 | N7: =I7*K7*Исходные!$B$19 -> 10348628 | O7: =I7*L7*Исходные!$B$20 -> 11367750
A8: Ведущий экономист | B8: 2 | C8: 120000 | D8: АУП | E8: ОХР | F8: =B8*C8*(1+Исходные!$B$11) -> 264000 | G8: =F8*ДЗП!$B$9 -> 35271.255 | H8: =(F8+G8)*Взносы!$B$8 -> 98160.972 | I8: =F8+G8+H8 -> 397432.23 | J8: 4.5335085 | K8: 12.023653 | L8: 12.352168 | M8: =I8*J8*Исходные!$B$18 -> 1947705.1 | N8: =I8*K8*Исходные!$B$19 -> 5519268.2 | O8: =I8*L8*Исходные!$B$20 -> 6062799.9
A9: Ведущий инженер-технолог | B9: 4 | C9: 150000 | D9: ИТР | E9: ОХР | F9: =B9*C9*(1+Исходные!$B$11) -> 660000 | G9: =F9*ДЗП!$B$9 -> 88178.138 | H9: =(F9+G9)*Взносы!$B$8 -> 245402.43 | I9: =F9+G9+H9 -> 993580.57 | J9: 4.5335085 | K9: 12.023653 | L9: 12.352168 | M9: =I9*J9*Исходные!$B$18 -> 4869262.9 | N9: =I9*K9*Исходные!$B$19 -> 13798171 | O9: =I9*L9*Исходные!$B$20 -> 15157000
A10: Инженер-конструктор 1 категории | B10: 4 | C10: 150000 | D10: ИТР | E10: ОХР | F10: =B10*C10*(1+Исходные!$B$11) -> 660000 | G10: =F10*ДЗП!$B$9 -> 88178.138 | H10: =(F10+G10)*Взносы!$B$8 -> 245402.43 | I10: =F10+G10+H10 -> 993580.57 | J10: 4.5335085 | K10: 12.023653 | L10: 12.352168 | M10: =I10*J10*Исходные!$B$18 -> 4869262.9 | N10: =I10*K10*Исходные!$B$19 -> 13798171 | O10: =I10*L10*Исходные!$B$20 -> 15157000
A11: Технолог 1 категории | B11: 5 | C11: 120000 | D11: ИТР | E11: ОХР | F11: =B11*C11*(1+Исходные!$B$11) -> 660000 | G11: =F11*ДЗП!$B$9 -> 88178.138 | H11: =(F11+G11)*Взносы!$B$8 -> 245402.43 | I11: =F11+G11+H11 -> 993580.57 | J11: 4.5335085 | K11: 12.023653 | L11: 12.352168 | M11: =I11*J11*Исходные!$B$18 -> 4869262.9 | N11: =I11*K11*Исходные!$B$19 -> 13798171 | O11: =I11*L11*Исходные!$B$20 -> 15157000
A12: Начальник производства | B12: 1 | C12: 200000 | D12: АУП | E12: ОПР | F12: =B12*C12*(1+Исходные!$B$11) -> 220000 | G12: =F12*ДЗП!$B$9 -> 29392.713 | H12: =(F12+G12)*Взносы!$B$8 -> 81800.81 | I12: =F12+G12+H12 -> 331193.52 | J12: 2.5952694 | K12: 12.023653 | L12: 12.352168 | M12: =I12*J12*Исходные!$B$18 -> 929158.86 | N12: =I12*K12*Исходные!$B$19 -> 4599390.2 | O12: =I12*L12*Исходные!$B$20 -> 5052333.2
A13: Начальник участка | B13: 5 | C13: 170000 | D13: ИТР | E13: ОПР | F13: =B13*C13*(1+Исходные!$B$11) -> 935000 | G13: =F13*ДЗП!$B$9 -> 124919.03 | H13: =(F13+G13)*Взносы!$B$8 -> 347653.44 | I13: =F13+G13+H13 -> 1407572.5 | J13: 2.5952694 | K13: 12.023653 | L13: 12.352168 | M13: =I13*J13*Исходные!$B$18 -> 3948925.1 | N13: =I13*K13*Исходные!$B$19 -> 19547408 | O13: =I13*L13*Исходные!$B$20 -> 21472416
A14: Старший мастер участка | B14: 7 | C14: 180000 | D14: ИТР | E14: ОПР | F14: =B14*C14*(1+Исходные!$B$11) -> 1386000 | G14: =F14*ДЗП!$B$9 -> 185174.09 | H14: =(F14+G14)*Взносы!$B$8 -> 515345.1 | I14: =F14+G14+H14 -> 2086519.2 | J14: 2.5952694 | K14: 12.023653 | L14: 12.352168 | M14: =I14*J14*Исходные!$B$18 -> 5853700.8 | N14: =I14*K14*Исходные!$B$19 -> 28976158 | O14: =I14*L14*Исходные!$B$20 -> 31829699
A15: Мастер участка | B15: 7 | C15: 130000 | D15: ИТР | E15: ОПР | F15: =B15*C15*(1+Исходные!$B$11) -> 1001000 | G15: =F15*ДЗП!$B$9 -> 133736.84 | H15: =(F15+G15)*Взносы!$B$8 -> 372193.68 | I15: =F15+G15+H15 -> 1506930.5 | J15: 2.5952694 | K15: 12.023653 | L15: 12.352168 | M15: =I15*J15*Исходные!$B$18 -> 4227672.8 | N15: =I15*K15*Исходные!$B$19 -> 20927225 | O15: =I15*L15*Исходные!$B$20 -> 22988116
... A21: Специалист по связям с общественностью | B21: 2 | C21: 80000 | D21: служащий | E21: КОМ | F21: =B21*C21*(1+Исходные!$B$11) -> 176000 | G21: =F21*ДЗП!$B$9 -> 23514.17 | H21: =(F21+G21)*Взносы!$B$8 -> 65440.648 | I21: =F21+G21+H21 -> 264954.82 | J21: 10.21682 | K21: 12.023653 | L21: 12.352168 | M21: =I21*J21*Исходные!$B$18 -> 2926262.3 | N21: =I21*K21*Исходные!$B$19 -> 3679512.2 | O21: =I21*L21*Исходные!$B$20 -> 4041866.6
A22: Итого | B22: =SUM(B4:B21) -> 77 | I22: =SUM(I4:I21) -> 16534837 | M22: =SUM(M4:M21) -> 61408873 | N22: =SUM(N4:N21) -> 2.2962456e+08 | O22: =SUM(O4:O21) -> 2.5223774e+08
A24: Общепроизводственные (руководство производством) | E24: ОПР | M24: =SUMIF($E$4:$E$21,$E24,M$4:M$21) -> 28455490 | N24: =SUMIF($E$4:$E$21,$E24,N$4:N$21) -> 1.4085632e+08 | O24: =SUMIF($E$4:$E$21,$E24,O$4:O$21) -> 1.5472771e+08
A25: Общехозяйственные (инженерная и управленческая группа) | E25: ОХР | M25: =SUMIF($E$4:$E$21,$E25,M$4:M$21) -> 30027121 | N25: =SUMIF($E$4:$E$21,$E25,N$4:N$21) -> 85088719 | O25: =SUMIF($E$4:$E$21,$E25,O$4:O$21) -> 93468165
A26: Коммерческие (связи с общественностью) | E26: КОМ | M26: =SUMIF($E$4:$E$21,$E26,M$4:M$21) -> 2926262.3 | N26: =SUMIF($E$4:$E$21,$E26,N$4:N$21) -> 3679512.2 | O26: =SUMIF($E$4:$E$21,$E26,O$4:O$21) -> 4041866.6
A28: Месяцы - от формирования проектной группы (ОХР), от начала корпусообработки (ОПР), от подписания договора (коммерческие) до передачи судна заказчику, по дорожной карте.

Sheet Обучение
A1: Обязательное обучение персонала
A3: Организация | B3: Тема | C3: Стоимость 2026, руб. | D3: Индекс | E3: Стоимость 2027, руб. | F3: Человек | G3: Итого, руб.
A4: АНО ДПО «Учебный центр «Перспектива» | B4: Эксплуатация электроустановок для испытаний и измерений | C4: 4200 | D4: 1.04 | E4: =C4*D4 -> 4368 | F4: 30 | G4: =E4*F4 -> 131040
A5: АНО ДПО «Прикамский институт безопасности» | B5: Поверка и калибровка средств измерений теплотехнических величин | C5: 8000 | D5: 1.04 | E5: =C5*D5 -> 8320 | F5: 15 | G5: =E5*F5 -> 124800
A6: АНО ДПО «ДВИПРАЗ» | B6: Поверка и калибровка средств геометрических измерений | C6: 526 | D6: 1.04 | E6: =C6*D6 -> 547.04 | F6: 25 | G6: =E6*F6 -> 13676
A7: ЧОУ ДПО «Учебный центр «Конфакт» | B7: Проверка знаний машиниста плавучего крана | C7: 2000 | D7: 1.04 | E7: =C7*D7 -> 2080 | F7: 35 | G7: =E7*F7 -> 72800
A8: ЧОУ ДПО «Морские системы» | B8: Подготовка по разделу A-VI/1 Кодекса ПДНВ | C8: 7300 | D8: 1.04 | E8: =C8*D8 -> 7592 | F8: 20 | G8: =E8*F8 -> 151840
A9: ООО МУИЦ «Меркурий» | B9: Специалист по пожарной профилактике | C9: 350 | D9: 1.04 | E9: =C9*D9 -> 364 | F9: 100 | G9: =E9*F9 -> 36400
A10: ЧОУ ДПО «Спутник» | B10: Техносферная безопасность, охрана труда | C10: 808 | D10: 1.04 | E10: =C10*D10 -> 840.32 | F10: 150 | G10: =E10*F10 -> 126048
A11: ЧОУ ДПО «Морские системы» | B11: Специалист по спасательным шлюпкам и плотам, раздел A-VI/2 Кодекса ПДНВ | C11: 3000 | D11: 1.04 | E11: =C11*D11 -> 3120 | F11: 30 | G11: =E11*F11 -> 93600
A12: ИП Климчук В. А. | B12: Обучение по охране труда, общий договор | C12: 376800 | D12: 1.04 | E12: =C12*D12 -> 391872 | F12: договор | G12: =E12 -> 391872
A13: ИП Лысенко И. М. | B13: Обучение по электробезопасности, общий договор | C13: 178020 | D13: 1.041 | E13: =C13*D13 -> 185318.82 | F13: договор | G13: =E13 -> 185318.82
A14: АНО ДПО «ПРОФАТОМЭНЕРГО» | B14: Обучение по радиационной безопасности, общий договор | C14: 306360 | D14: 1.04 | E14: =C14*D14 -> 318614.4 | F14: договор | G14: =E14 -> 318614.4
A15: Итого | G15: =SUM(G4:G14) -> 1646009.2

Sheet Маркетинг
A1: Маркетинг и продвижение
A3: Исполнитель | B3: Вид | C3: Руб. в месяц | D3: Как выполняется
A4: Метрополитен Санкт-Петербурга | B4: Реклама на путевых щитах 4 × 2 м | C4: 124000 | D4: макет - отдел по связям с общественностью верфи
A5: АО «Адмиралтейские верфи» | B5: Буклеты и раздаточная продукция | C5: 3000 | D5: типография предприятия, 100 буклетов А4 в месяц по 30 руб., выставки и конференции
A6: АО «Адмиралтейские верфи» | B6: Реклама в социальных сетях | C6: 0 | D6: силами сотрудников в Telegram, MAX и ВКонтакте
A7: Итого в месяц | C7: =SUM(C4:C6) -> 127000
A9: Год | B9: Месяцев от договора до передачи судна | C9: Затраты, руб.
A10: 2027 | B10: 10.21682 | C10: =Маркетинг!$C$7*B10 -> 1297536.1
A11: 2028 | B11: 12.023653 | C11: =Маркетинг!$C$7*B11 -> 1527003.9
A12: 2029 | B12: 12.352168 | C12: =Маркетинг!$C$7*B12 -> 1568725.4

Sheet НИОКР
A1: НИОКР - проектирование судна проектным бюро
A3: Ставка инженера-конструктора с премией, ДЗП и взносами, руб./ч | B3: ='АУП и ИТР'!C10*(1+Исходные!$B$11)/Исходные!$B$12*(1+ДЗП!$B$9)*(1+Взносы!$B$8) -> 1508.4725
A5: Стадия | B5: Трудоёмкость, чел·ч | C5: Задача дорожной карты | D5: Доля 2026 | E5: Доля 2027 | F5: Затраты 2026, руб. | G5: Затраты 2027, руб. | H5: Итого, руб.
A6: Эскизный проект | B6: 1628.955 | C6: 3.2. Эскизирование | D6: 1 | E6: 0 | F6: =B6*$B$3*D6*Исходные!$B$17 -> 2457233.9 | G6: =B6*$B$3*E6*Исходные!$B$18 -> 0 | H6: =F6+G6 -> 2457233.9
A7: Технический проект | B7: 6515.8202 | C7: 3.4. ОКР (опытно-конструкторская работа) | D7: 0.65 | E7: 0.35 | F7: =B7*$B$3*D7*Исходные!$B$17 -> 6388808.2 | G7: =B7*$B$3*E7*Исходные!$B$18 -> 3718777.8 | H7: =F7+G7 -> 10107586
A8: Рабочая КД | B8: 24434.326 | C8: 6. Составление рабочей конструкторской документации (схемы систем, чертежи) | D8: 0 | E8: 1 | F8: =B8*$B$3*D8*Исходные!$B$17 -> 0 | G8: =B8*$B$3*E8*Исходные!$B$18 -> 39844048 | H8: =F8+G8 -> 39844048
A9: Итого | B9: =SUM(B6:B8) -> 32579.101 | F9: =SUM(F6:F8) -> 8846042.1 | G9: =SUM(G6:G8) -> 43562826 | H9: =SUM(H6:H8) -> 52408868

Sheet Капзатраты
A1: Капитальные затраты - цех фундаментов-замков в арендованном ангаре
A3: Оборудование (покупка) | B3: Кол. | C3: Цена, руб. | D3: Сумма, руб.
A4: Печь индукционная тигельная ИСТ-0,16 с преобразователем частоты и градирней | B4: 1 | C4: 6800000 | D4: =B4*C4 -> 6800000
A5: Ковш разливочный чайниковый 0,25 т и стенд подогрева | B5: 1 | C5: 380000 | D5: =B5*C5 -> 380000
A6: Смеситель ХТС лопастной 0,1 м³ | B6: 1 | C6: 450000 | D6: =B6*C6 -> 450000
A7: Стол вибрационный формовочный 1,0 × 1,0 м | B7: 1 | C7: 220000 | D7: =B7*C7 -> 220000
A8: Опоки сварные 600 × 400 × 160/80 со штырями | B8: 8 | C8: 25000 | D8: =B8*C8 -> 200000
A9: Решётка выбивная инерционная | B9: 1 | C9: 320000 | D9: =B9*C9 -> 320000
A10: Пневмошлифмашины угловые DAEWOO (круг 180 мм) и прямые Daewoo DG-38LS | B10: 5 | C10: 18000 | D10: =B10*C10 -> 90000
A11: Компрессор винтовой 11 кВт, 1,6 м³/мин, 8 бар, с ресивером | B11: 1 | C11: 650000 | D11: =B11*C11 -> 650000
A12: Электропечь камерная сопротивления ПН-12-2 | B12: 1 | C12: 950000 | D12: =B12*C12 -> 950000
A13: Машина плазменной резки с ЧПУ NUMOREX NXB, поле 2000 × 6000 мм, источник 125 А | B13: 1 | C13: 4800000 | D13: =B13*C13 -> 4800000
A14: Станок вертикально-сверлильный 2Н135 | B14: 1 | C14: 950000 | D14: =B14*C14 -> 950000
A15: Станок токарно-винторезный 16К20, РМЦ 1000 | B15: 1 | C15: 2900000 | D15: =B15*C15 -> 2900000
... A21: Стеллажи, поддоны, тележки гидравлические | B21: 1 | C21: 220000 | D21: =B21*C21 -> 220000
A22: Итого оборудование | D22: =SUM(D4:D21) -> 22070000
A24: Площадка | B24: м² | C24: Руб./м² в месяц | D24: Месяцев
A25: Аренда ангара под цех узла | B25: 864 | C25: 650 | D25: 3.6
A26: Аренда за срок, руб. | D26: =B25*C25*D25 -> 2021760
A28: Судно строится на действующих мощностях верфи: стапель, достроечная набережная, цеха. Аренда ангара входит в себестоимость фундаментов-замков.

Sheet Безубыточность
A1: Серийное судно и точка безубыточности
A3: Показатель | B3: Значение | C3: Примечание
A4: Материальные затраты, руб. | B4: =Калькуляция!B4 -> 5.8696224e+08 | C4: как у головного
A5: Оплата труда с взносами головного, руб. | B5: =Калькуляция!B8+Калькуляция!B11 -> 1.0845557e+09
A6: Оплата труда с взносами серийного, руб. | B6: =B5/Исходные!$B$10 -> 8.3427364e+08 | C6: без коэффициента головного
A7: Прямые затраты серийного судна, руб. | B7: =B4+B6 -> 1.4212359e+09 | C7: переменные
A8: Постоянные затраты в год, руб. | B8: ='АУП и ИТР'!I22*12+Маркетинг!$C$7*12 -> 1.9994204e+08 | C8: АУП и ИТР, маркетинг
A9: Себестоимость серийного судна при темпе одно в год, руб. | B9: =B7+B8 -> 1.6211779e+09
A10: Цена серийного судна без НДС, руб. | B10: =B9*(1+Исходные!$B$13) -> 1.8643546e+09 | C10: с рентабельностью головного
A11: Маржинальный доход с судна, руб. | B11: =B10-B7 -> 4.4311873e+08
A12: Точка безубыточности, судов в год | B12: =B8/B11 -> 0.4512155 | C12: производство прибыльно с одного судна в год

Sheet Окупаемость
A1: Денежный поток программы: головное и серийные суда, руб.
A3: Год | B3: НИОКР | C3: Капзатраты | D3: Затраты на постройку | E3: Выручка без НДС | F3: Денежный поток | G3: Коэф. дисконт. | H3: Дисконтированный поток | I3: Накопленный поток | J3: Накопленный дисконт. | K3: Окуп. | L3: Окуп. диск.
A4: 2026 | B4: =НИОКР!F9 -> 8846042.1 | C4: 0 | D4: 0 | E4: 0 | F4: =E4-B4-C4-D4 -> -8846042.1 | G4: =1/(1+Исходные!$B$14)^(A4-2026) -> 1 | H4: =F4*G4 -> -8846042.1 | I4: =0+F4 -> -8846042.1 | J4: =0+H4 -> -8846042.1
A5: 2027 | B5: =НИОКР!G9 -> 43562826 | C5: =Капзатраты!D22 -> 22070000 | D5: =Калькуляция!C16 -> 7.4085375e+08 | E5: 0 | F5: =E5-B5-C5-D5 -> -8.0648658e+08 | G5: =1/(1+Исходные!$B$14)^(A5-2026) -> 0.86956522 | H5: =F5*G5 -> -7.0129268e+08 | I5: =I4+F5 -> -8.1533262e+08 | J5: =J4+H5 -> -7.1013872e+08 | K5: =IF(AND(I5>=0,I4<0),A5,"") | L5: =IF(AND(J5>=0,J4<0),A5,"")
A6: 2028 | B6: 0 | C6: 0 | D6: =Калькуляция!D16 -> 8.396662e+08 | E6: 0 | F6: =E6-B6-C6-D6 -> -8.396662e+08 | G6: =1/(1+Исходные!$B$14)^(A6-2026) -> 0.75614367 | H6: =F6*G6 -> -6.3490828e+08 | I6: =I5+F6 -> -1.6549988e+09 | J6: =J5+H6 -> -1.345047e+09 | K6: =IF(AND(I6>=0,I5<0),A6,"") | L6: =IF(AND(J6>=0,J5<0),A6,"")
A7: 2029 | B7: 0 | C7: 0 | D7: =Калькуляция!E16 -> 6.4030846e+08 | E7: 0 | F7: =E7-B7-C7-D7 -> -6.4030846e+08 | G7: =1/(1+Исходные!$B$14)^(A7-2026) -> 0.65751623 | H7: =F7*G7 -> -4.210132e+08 | I7: =I6+F7 -> -2.2953073e+09 | J7: =J6+H7 -> -1.7660602e+09 | K7: =IF(AND(I7>=0,I6<0),A7,"") | L7: =IF(AND(J7>=0,J6<0),A7,"")
A8: 2030 | B8: 0 | C8: 0 | D8: 0 | E8: =Калькуляция!B18 -> 2.5539527e+09 | F8: =E8-B8-C8-D8 -> 2.5539527e+09 | G8: =1/(1+Исходные!$B$14)^(A8-2026) -> 0.57175325 | H8: =F8*G8 -> 1.4602307e+09 | I8: =I7+F8 -> 2.5864539e+08 | J8: =J7+H8 -> -3.0582947e+08 | K8: =IF(AND(I8>=0,I7<0),A8,"") -> 2030 | L8: =IF(AND(J8>=0,J7<0),A8,"")
A9: 2031 | B9: 0 | C9: 0 | D9: =Безубыточность!B9*(1+Исходные!$B$16)^(A9-2029) -> 1.8215555e+09 | E9: =Безубыточность!B10*(1+Исходные!$B$16)^(A9-2029) -> 2.0947888e+09 | F9: =E9-B9-C9-D9 -> 2.7323333e+08 | G9: =1/(1+Исходные!$B$14)^(A9-2026) -> 0.49717674 | H9: =F9*G9 -> 1.3584525e+08 | I9: =I8+F9 -> 5.3187872e+08 | J9: =J8+H9 -> -1.6998422e+08 | K9: =IF(AND(I9>=0,I8<0),A9,"") | L9: =IF(AND(J9>=0,J8<0),A9,"")
A10: 2032 | B10: 0 | C10: 0 | D10: =Безубыточность!B9*(1+Исходные!$B$16)^(A10-2029) -> 1.9308488e+09 | E10: =Безубыточность!B10*(1+Исходные!$B$16)^(A10-2029) -> 2.2204762e+09 | F10: =E10-B10-C10-D10 -> 2.8962733e+08 | G10: =1/(1+Исходные!$B$14)^(A10-2026) -> 0.4323276 | H10: =F10*G10 -> 1.2521389e+08 | I10: =I9+F10 -> 8.2150605e+08 | J10: =J9+H10 -> -44770336 | K10: =IF(AND(I10>=0,I9<0),A10,"") | L10: =IF(AND(J10>=0,J9<0),A10,"")
A11: 2033 | B11: 0 | C11: 0 | D11: =Безубыточность!B9*(1+Исходные!$B$16)^(A11-2029) -> 2.0466998e+09 | E11: =Безубыточность!B10*(1+Исходные!$B$16)^(A11-2029) -> 2.3537047e+09 | F11: =E11-B11-C11-D11 -> 3.0700497e+08 | G11: =1/(1+Исходные!$B$14)^(A11-2026) -> 0.37593704 | H11: =F11*G11 -> 1.1541454e+08 | I11: =I10+F11 -> 1.128511e+09 | J11: =J10+H11 -> 70644202 | K11: =IF(AND(I11>=0,I10<0),A11,"") | L11: =IF(AND(J11>=0,J10<0),A11,"") -> 2033
A12: 2034 | B12: 0 | C12: 0 | D12: =Безубыточность!B9*(1+Исходные!$B$16)^(A12-2029) -> 2.1695018e+09 | E12: =Безубыточность!B10*(1+Исходные!$B$16)^(A12-2029) -> 2.494927e+09 | F12: =E12-B12-C12-D12 -> 3.2542526e+08 | G12: =1/(1+Исходные!$B$14)^(A12-2026) -> 0.32690177 | H12: =F12*G12 -> 1.063821e+08 | I12: =I11+F12 -> 1.4539363e+09 | J12: =J11+H12 -> 1.770263e+08 | K12: =IF(AND(I12>=0,I11<0),A12,"") | L12: =IF(AND(J12>=0,J11<0),A12,"")
A13: 2035 | B13: 0 | C13: 0 | D13: =Безубыточность!B9*(1+Исходные!$B$16)^(A13-2029) -> 2.2996719e+09 | E13: =Безубыточность!B10*(1+Исходные!$B$16)^(A13-2029) -> 2.6446226e+09 | F13: =E13-B13-C13-D13 -> 3.4495078e+08 | G13: =1/(1+Исходные!$B$14)^(A13-2026) -> 0.28426241 | H13: =F13*G13 -> 98056541 | I13: =I12+F13 -> 1.7988871e+09 | J13: =J12+H13 -> 2.7508284e+08 | K13: =IF(AND(I13>=0,I12<0),A13,"") | L13: =IF(AND(J13>=0,J12<0),A13,"")
A15: NPV | F15: =SUM(H4:H13) -> 2.7508284e+08
A16: Инвестиции до первой выручки, дисконтированные | F16: =-SUMIF(A4:A13,"<2030",H4:H13) -> 1.7660602e+09
A17: PI | F17: =1+F15/F16 -> 1.1557607
A18: IRR | F18: =IRR(F4:F13) -> 0.20804837
A19: Срок окупаемости, лет от 2026 | F19: =MIN(K4:K13)-2026 -> 4
A20: Дисконтированный срок окупаемости, лет от 2026 | F20: =MIN(L4:L13)-2026 -> 7
